doconf
