Metadata-Version: 1.1
Name: doconf
Version: 0.2.0
Summary: Configuration specified through documentation, supporting multiple formats.
Home-page: https://github.com/johannestaas/doconf
Author: Johan Nestaas
Author-email: johannestaas@gmail.com
License: GPLv3
Keywords: documentation configuration config conf cfg
Platform: UNKNOWN
Classifier: Development Status :: 3 - Alpha
Classifier: Environment :: Console
Classifier: Environment :: X11 Applications :: Qt
Classifier: Environment :: MacOS X
Classifier: Environment :: Win32 (MS Windows)
Classifier: Operating System :: POSIX
Classifier: Operating System :: MacOS :: MacOS X
Classifier: Operating System :: Microsoft :: Windows
Classifier: Programming Language :: Python
